multiformats_cid/__init__.py
multiformats_cid/cid.py
multiformats_cid/py.typed
py_multiformats_cid-0.4.4.dist-info/AUTHORS.rst
py_multiformats_cid-0.4.4.dist-info/LICENSE
py_multiformats_cid-0.4.4.dist-info/METADATA
py_multiformats_cid-0.4.4.dist-info/WHEEL
py_multiformats_cid-0.4.4.dist-info/top_level.txt
py_multiformats_cid-0.4.4.dist-info/RECORD
