Metadata-Version: 2.1
Name: py-multiformats-cid
Version: 0.4.4
Summary: Self-describing content-addressed identifiers for distributed systems
Home-page: https://github.com/pinnaculum/py-multiformats-cid
Author: Dhruv Baldawa
Author-email: dhruv@dhruvb.com
License: MIT license
Keywords: cid
Classifier: Development Status :: 2 - Pre-Alpha
Classifier: Intended Audience :: Developers
Classifier: License :: OSI Approved :: MIT License
Classifier: Natural Language :: English
Classifier: Programming Language :: Python :: 3
Classifier: Programming Language :: Python :: 3.6
Classifier: Programming Language :: Python :: 3.7
Classifier: Programming Language :: Python :: 3.8
Classifier: Programming Language :: Python :: 3.9
Requires-Python: >=3.6
License-File: LICENSE
License-File: AUTHORS.rst
Requires-Dist: base58
Requires-Dist: py-multibase
Requires-Dist: py-multicodec
Requires-Dist: morphys
Requires-Dist: py-multihash
